robbytorch/__init__.py
robbytorch/attack_steps.py
robbytorch/input_transforms.py
robbytorch/metrics.py
robbytorch/notebook.py
robbytorch/profiler.py
robbytorch/run.py
robbytorch/train.py
robbytorch/transforms.py
robbytorch/tutorial.py
robbytorch/utils.py
robbytorch/video.py
robbytorch/visualization.py
robbytorch/writers.py
robbytorch/datasets/__init__.py
robbytorch/datasets/clips_from_videos.py
robbytorch/datasets/dict_dataset.py
robbytorch/datasets/utils.py
robbytorch/models/__init__.py
robbytorch/models/robustness/__init__.py
robbytorch/models/robustness/custom_modules.py
robbytorch/models/robustness/resnet.py
robbytorch-0.4.1.dist-info/LICENSE
robbytorch-0.4.1.dist-info/METADATA
robbytorch-0.4.1.dist-info/WHEEL
robbytorch-0.4.1.dist-info/top_level.txt
robbytorch-0.4.1.dist-info/RECORD
