Metadata-Version: 2.1
Name: robbytorch
Version: 0.4.1
Summary: Cool package for robust AI
Home-page: https://github.com/mim-solutions/robbytorch
Author: MIM Solutions
Author-email: maciej.satkiewicz@mim-solutions.pl
License: MIT
Project-URL: Bug Reports, https://github.com/mim-solutions/robbytorch/issues
Keywords: pytorch,neural-networks,deep-learning,robust-learning,transfer-learning
Platform: UNKNOWN
Classifier: Development Status :: 4 - Beta
Classifier: Intended Audience :: Developers
Classifier: Topic :: Software Development :: Build Tools
Classifier: License :: OSI Approved :: MIT License
Classifier: Programming Language :: Python :: 3
Classifier: Programming Language :: Python :: 3.7
Requires-Python: >=3.7, <4
License-File: LICENSE
Requires-Dist: numpy
Requires-Dist: matplotlib
Requires-Dist: tqdm
Requires-Dist: pandas
Requires-Dist: seaborn
Requires-Dist: livelossplot
Requires-Dist: mypy
Requires-Dist: mlflow
Requires-Dist: dill
Requires-Dist: pyinstrument
Requires-Dist: ipywidgets
Requires-Dist: opencv-python-headless
Requires-Dist: wandb
